[
{
  "model": "webapp.mission",
  "pk": 1,
  "fields": {
    "summary": "bla bla",
    "description": "blq bla bla bla",
    "status": 2,
    "type": 2,
    "project": 3,
    "created_at": "2019-09-27T10:56:09.929Z",
    "updated_at": "2019-10-11T09:38:33.159Z"
  }
},
{
  "model": "webapp.mission",
  "pk": 3,
  "fields": {
    "summary": "olololo",
    "description": "scholarshipsasf",
    "status": 2,
    "type": 3,
    "project": 3,
    "created_at": "2019-09-27T11:04:27.432Z",
    "updated_at": "2019-10-11T09:38:36.446Z"
  }
},
{
  "model": "webapp.mission",
  "pk": 5,
  "fields": {
    "summary": "ragby",
    "description": "lolfokgotrkg",
    "status": 2,
    "type": 3,
    "project": 2,
    "created_at": "2019-09-27T11:05:09.378Z",
    "updated_at": "2019-10-11T09:38:38.987Z"
  }
},
{
  "model": "webapp.mission",
  "pk": 6,
  "fields": {
    "summary": "basketbal",
    "description": "frog",
    "status": 2,
    "type": 3,
    "project": 1,
    "created_at": "2019-09-27T11:05:31.885Z",
    "updated_at": "2019-10-11T09:38:41.633Z"
  }
},
{
  "model": "webapp.mission",
  "pk": 7,
  "fields": {
    "summary": "lolololo",
    "description": "afesgrd",
    "status": 2,
    "type": 3,
    "project": 1,
    "created_at": "2019-10-07T14:17:20.501Z",
    "updated_at": "2019-10-11T09:27:11.030Z"
  }
},
{
  "model": "webapp.status",
  "pk": 1,
  "fields": {
    "status": "new"
  }
},
{
  "model": "webapp.status",
  "pk": 2,
  "fields": {
    "status": "in progress"
  }
},
{
  "model": "webapp.status",
  "pk": 3,
  "fields": {
    "status": "done"
  }
},
{
  "model": "webapp.status",
  "pk": 4,
  "fields": {
    "status": "lol"
  }
},
{
  "model": "webapp.status",
  "pk": 7,
  "fields": {
    "status": "rgasdf"
  }
},
{
  "model": "webapp.status",
  "pk": 9,
  "fields": {
    "status": "dfds"
  }
},
{
  "model": "webapp.type",
  "pk": 2,
  "fields": {
    "type": "bug"
  }
},
{
  "model": "webapp.type",
  "pk": 3,
  "fields": {
    "type": "enhancement"
  }
},
{
  "model": "webapp.type",
  "pk": 4,
  "fields": {
    "type": "task"
  }
},
{
  "model": "webapp.type",
  "pk": 6,
  "fields": {
    "type": "hot"
  }
},
{
  "model": "webapp.type",
  "pk": 9,
  "fields": {
    "type": "lolo"
  }
},
{
  "model": "webapp.type",
  "pk": 11,
  "fields": {
    "type": "asfaf"
  }
},
{
  "model": "webapp.type",
  "pk": 12,
  "fields": {
    "type": "asfaf+aa"
  }
},
{
  "model": "webapp.type",
  "pk": 13,
  "fields": {
    "type": "esffas"
  }
},
{
  "model": "webapp.type",
  "pk": 15,
  "fields": {
    "type": "new type"
  }
},
{
  "model": "webapp.project",
  "pk": 1,
  "fields": {
    "name": "1",
    "description": "first project lololo",
    "created_at": "2019-10-11T09:21:21.482Z",
    "updated_at": "2019-10-11T09:21:21.482Z"
  }
},
{
  "model": "webapp.project",
  "pk": 2,
  "fields": {
    "name": "2",
    "description": "second project olololo",
    "created_at": "2019-10-11T09:21:38.455Z",
    "updated_at": "2019-10-11T09:21:38.455Z"
  }
},
{
  "model": "webapp.project",
  "pk": 3,
  "fields": {
    "name": "3",
    "description": "",
    "created_at": "2019-10-11T09:26:39.557Z",
    "updated_at": "2019-10-11T09:26:39.557Z"
  }
},
{
  "model": "auth.user",
  "pk": 1,
  "fields": {
    "password": "pbkdf2_sha256$150000$CDPtgpcu9r1G$BKZYDG2+xhhxjnUgRKCACpNWnNZYtgXC6DVI5Idwmgw=",
    "last_login": "2019-10-11T09:19:20.172Z",
    "is_superuser": true,
    "username": "admin",
    "first_name": "",
    "last_name": "",
    "email": "",
    "is_staff": true,
    "is_active": true,
    "date_joined": "2019-09-27T08:40:33.200Z",
    "groups": [],
    "user_permissions": []
  }
}
]
